helloworld.py
dfmaps/__init__.py
dfmaps/poi/__init__.py
dfmaps/poi/points_of_interest.py
dfmaps2-1.5.data/scripts/hello-pybuilder
string_funcs/__init__.py
string_funcs/stringLength.py
string_funcs/stringToLower.py
string_funcs/stringToUpper.py
dfmaps2-1.5.dist-info/METADATA
dfmaps2-1.5.dist-info/WHEEL
dfmaps2-1.5.dist-info/namespace_packages.txt
dfmaps2-1.5.dist-info/top_level.txt
dfmaps2-1.5.dist-info/zip-safe
dfmaps2-1.5.dist-info/RECORD
