Metadata-Version: 2.1
Name: dfmaps2
Version: 1.5
Summary: Trabajo Final de grado Isabela San Jose, representacion de dataframes en mapas
Home-page: https://github.com/
Author: UNKNOWN
Author-email: UNKNOWN
License: None
Platform: UNKNOWN
Classifier: Development Status :: 3 - Alpha
Classifier: Programming Language :: Python
